agentize/__init__.py
agentize/lazy.py
agentize/model.py
agentize/py.typed
agentize/utils.py
agentize/agents/__init__.py
agentize/agents/dummy_agent.py
agentize/prompts/__init__.py
agentize/prompts/financial_research.py
agentize/prompts/meta.py
agentize/prompts/research.py
agentize/prompts/summary.py
agentize/tools/__init__.py
agentize/tools/boto3.py
agentize/tools/duckduckgo.py
agentize/tools/firecrawl.py
agentize/tools/markitdown.py
agentize/tools/telegraph.py
agentize/tools/tripplus.py
agentize/tools/wise.py
agentize-0.1.0.dist-info/METADATA
agentize-0.1.0.dist-info/WHEEL
agentize-0.1.0.dist-info/licenses/LICENSE
agentize-0.1.0.dist-info/RECORD
