Metadata-Version: 2.4
Name: agentize
Version: 0.1.0
Author-email: narumi <toucans-cutouts0f@icloud.com>
License-File: LICENSE
Requires-Python: >=3.11
Requires-Dist: aiolimiter>=1.2.1
Requires-Dist: boto3>=1.38.13
Requires-Dist: duckduckgo-search>=8.0.1
Requires-Dist: firecrawl-py>=2.5.3
Requires-Dist: loguru>=0.7.3
Requires-Dist: openai-agents>=0.0.14
Requires-Dist: requests>=2.32.3
Requires-Dist: tripplus>=0.1.1
Requires-Dist: ua-generator>=2.0.5
Requires-Dist: wisest>=0.15.0
Requires-Dist: your-telegraph>=0.2.1
Provides-Extra: all
Requires-Dist: langfuse>=2.60.5; extra == 'all'
Requires-Dist: markitdown>=0.1.1; extra == 'all'
Provides-Extra: langfuse
Requires-Dist: logfire>=3.14.1; extra == 'langfuse'
Requires-Dist: nest-asyncio>=1.6.0; extra == 'langfuse'
Provides-Extra: markitdown
Requires-Dist: markitdown>=0.1.1; extra == 'markitdown'
